LICENSE.md
MANIFEST.in
README.md
pyproject.toml
popcornn/__init__.py
popcornn/popcornn.py
popcornn.egg-info/PKG-INFO
popcornn.egg-info/SOURCES.txt
popcornn.egg-info/dependency_links.txt
popcornn.egg-info/requires.txt
popcornn.egg-info/top_level.txt
popcornn/optimization/__init__.py
popcornn/optimization/initialize_path.py
popcornn/optimization/path_optimizer.py
popcornn/optimization/update_minima.py
popcornn/paths/__init__.py
popcornn/paths/base_path.py
popcornn/paths/linear.py
popcornn/paths/mlp.py
popcornn/potentials/__init__.py
popcornn/potentials/ani.py
popcornn/potentials/base_potential.py
popcornn/potentials/chgnet.py
popcornn/potentials/constant.py
popcornn/potentials/escaip.py
popcornn/potentials/harmonic.py
popcornn/potentials/leftnet.py
popcornn/potentials/lennard_jones.py
popcornn/potentials/mace.py
popcornn/potentials/morse.py
popcornn/potentials/muller_brown.py
popcornn/potentials/newtonnet.py
popcornn/potentials/orb.py
popcornn/potentials/repel.py
popcornn/potentials/schwefel.py
popcornn/potentials/sphere.py
popcornn/potentials/uma.py
popcornn/potentials/wolfe_schlegel.py
popcornn/tools/__init__.py
popcornn/tools/arg_parser.py
popcornn/tools/ase.py
popcornn/tools/configs.py
popcornn/tools/images.py
popcornn/tools/integrator.py
popcornn/tools/logging.py
popcornn/tools/metrics.py
popcornn/tools/scheduler.py
popcornn/tools/tests.py
popcornn/tools/visualize.py
tests/test_images.py
tests/test_initialize_path.py
tests/test_ode_functions.py
tests/test_paths.py
tests/test_potentials.py
tests/test_ts_search.py