Metadata-Version: 2.4
Name: popcornn
Version: 0.1.0
Summary: Path Optimization with a Continuous Representation Neural Network (popcornn) optimizes molecular reaction paths along analytic and MLIP potentials.
Author-email: Kareem Hegazy <khegazy@berkeley.edu>, "Eric C.-Y. Yuan" <ericyuan@berkeley.edu>, Anup Kumar <anukumar94663@gmail.com>, Dmitriy Morozov <dmitriy@mrzv.org>, Michael Mahoney <mmahoney@stat.berkeley.edu>, Teresa Head-Gordon <thg@berkeley.edu>, "Samuel M. Blau" <smblau@lbl.gov>
License: CC-BY 4.0
Project-URL: repository, https://github.com/khegazy/popcornn
Project-URL: documentation, https://khegazy.github.io/popcornn/
Project-URL: changelog, https://github.com/khegazy/popcornn/blob/main/CHANGELOG.md
Keywords: Chemistry,Transition State,Reaction path,Minimum Energy Path,Geodesic
Classifier: Development Status :: 3 - Alpha
Classifier: Intended Audience :: Science/Research
Classifier: Programming Language :: Python :: 3
Classifier: Intended Audience :: Science/Research
Classifier: Topic :: Scientific/Engineering
Classifier: Operating System :: Microsoft :: Windows
Classifier: Operating System :: Unix
Classifier: Operating System :: MacOS
Requires-Python: >=3.10
License-File: LICENSE.md
Requires-Dist: numpy
Requires-Dist: torch
Requires-Dist: torch_geometric
Requires-Dist: matplotlib
Requires-Dist: ase
Requires-Dist: tqdm
Requires-Dist: pytest
Requires-Dist: pytest-cov
Requires-Dist: PyYAML
Requires-Dist: torchpathdiffeq
Requires-Dist: fairchem-core>=2.4.0
Provides-Extra: dev
Requires-Dist: pytest>=7.4.0; extra == "dev"
Requires-Dist: pytest-cov>=3.0.0; extra == "dev"
Requires-Dist: ruff>=0.0.285; extra == "dev"
Provides-Extra: docs
Requires-Dist: mkdocs-material>=9.4.0; extra == "docs"
Requires-Dist: mkdocstrings[python]>=0.22.0; extra == "docs"
Requires-Dist: mkdocs-gen-files>=0.5.0; extra == "docs"
Requires-Dist: mkdocs-literate-nav>=0.6.0; extra == "docs"
Requires-Dist: pillow>=10.0.0; extra == "docs"
Requires-Dist: cairosvg>=2.7.1; extra == "docs"
Dynamic: license-file
